pymolPy3/__init__.py
pymolPy3/pymolPy3.py
pymolPy3-0.1.2.dist-info/LICENSE
pymolPy3-0.1.2.dist-info/METADATA
pymolPy3-0.1.2.dist-info/WHEEL
pymolPy3-0.1.2.dist-info/top_level.txt
pymolPy3-0.1.2.dist-info/RECORD
