Metadata-Version: 2.1
Name: pymolPy3
Version: 0.1.2
Summary: A PyMOL wrapper in Python3.
Home-page: https://github.com/carbonscott/pymolPy3
Author: Cong Wang
Author-email: wangimagine@gmail.com
License: UNKNOWN
Keywords: PDB,structure biology,protein,molecular graphics
Platform: UNKNOWN
Classifier: Programming Language :: Python :: 3
Classifier: License :: OSI Approved :: MIT License
Classifier: Operating System :: OS Independent
Requires-Python: >=3.6
